AUTHORS.md
LICENSE
MANIFEST.in
README.md
requirements.txt
setup.py
leeroy/__init__.py
leeroy/app.py
leeroy/base.py
leeroy/cron.py
leeroy/github.py
leeroy/jenkins.py
leeroy/retry.py
leeroy/scripts.py
leeroy/settings.py
leeroy.egg-info/PKG-INFO
leeroy.egg-info/SOURCES.txt
leeroy.egg-info/dependency_links.txt
leeroy.egg-info/entry_points.txt
leeroy.egg-info/not-zip-safe
leeroy.egg-info/requires.txt
leeroy.egg-info/top_level.txt